agent_mem/__init__.py
app/__init__.py
app/main.py
app/api/__init__.py
app/api/deps/__init__.py
app/api/deps/db.py
app/api/routes/__init__.py
app/api/routes/health.py
app/api/routes/memory.py
app/auto/__init__.py
app/auto/extractors.py
app/auto/models.py
app/chat/__init__.py
app/chat/chat_memory.py
app/chat/config.py
app/cli/evals.py
app/cli/main.py
app/core/__init__.py
app/core/client.py
app/db/__init__.py
app/db/base.py
app/db/init_db.py
app/db/session.py
app/evals/assertions.py
app/evals/dataset.py
app/evals/diff.py
app/evals/io.py
app/evals/judge.py
app/evals/judge_prompts.py
app/evals/replay.py
app/evals/runner.py
app/evals/suite.py
app/models/__init__.py
app/models/memory.py
app/rules/__init__.py
app/rules/models.py
app/schemas/experience.py
app/schemas/memory.py
app/services/embedding.py
app/services/event_service.py
app/services/memory_service.py
app/services/pii.py
app/services/scoring.py
app/session/budget.py
app/session/context.py
app/session/models.py
app/session/session.py
app/session/summarizer.py
app/session/summary_prompts.py
app/session/tokens.py
app/utils/experience.py
app/utils/text.py
app/utils/time.py
memory_os/__init__.py
mengram/__init__.py
mengram-0.1.4.dist-info/METADATA
mengram-0.1.4.dist-info/WHEEL
mengram-0.1.4.dist-info/entry_points.txt
mengram-0.1.4.dist-info/top_level.txt
mengram-0.1.4.dist-info/RECORD
