Metadata-Version: 2.4
Name: mengram
Version: 0.1.4
Summary: Human-like memory engine for LLM agents
Author: Dhruv Arora
Requires-Python: >=3.9
Requires-Dist: sqlalchemy
Requires-Dist: pydantic>=2
Requires-Dist: numpy
Provides-Extra: embeddings
Requires-Dist: sentence-transformers; extra == "embeddings"
Provides-Extra: full
Requires-Dist: sentence-transformers; extra == "full"
Provides-Extra: evals
Requires-Dist: sqlalchemy>=2; extra == "evals"
Requires-Dist: pydantic>=2; extra == "evals"
Requires-Dist: numpy; extra == "evals"
Provides-Extra: server
Requires-Dist: fastapi<0.116,>=0.115; extra == "server"
Requires-Dist: uvicorn; extra == "server"
